GramophoneTools/__init__.py
GramophoneTools/shortcuts.py
GramophoneTools/Comms/Gramophone.py
GramophoneTools/Comms/__init__.py
GramophoneTools/Comms/libusb-1.0.dll
GramophoneTools/LinMaze/Event.py
GramophoneTools/LinMaze/Frame.py
GramophoneTools/LinMaze/Level.py
GramophoneTools/LinMaze/LinMaze.py
GramophoneTools/LinMaze/Rule.py
GramophoneTools/LinMaze/Zone.py
GramophoneTools/LinMaze/__init__.py
GramophoneTools/LinMaze/perlin.py
GramophoneTools/LinMaze/perlin32.dll
GramophoneTools/LinMaze/perlin64.dll
GramophoneTools/LinMaze/Tools/Stopwatch.py
GramophoneTools/LinMaze/Tools/Timer.py
GramophoneTools/LinMaze/Tools/filehandler.py
GramophoneTools/LinMaze/Tools/progressbar.py
GramophoneTools/LinMaze/res/icon.png
GramophoneTools/Recorder/Recorder.py
GramophoneTools/Recorder/__init__.py
GramophoneTools/Recorder/__main__.py
GramophoneTools/Recorder/about.ui
GramophoneTools/Recorder/device_info.ui
GramophoneTools/Recorder/license.ui
GramophoneTools/Recorder/logger.py
GramophoneTools/Recorder/main.ui
GramophoneTools/Recorder/resources_rc.py
GramophoneTools/Recorder/settings.ui
GramophoneTools/docs/.buildinfo
GramophoneTools/docs/.nojekyll
GramophoneTools/docs/comms.html
GramophoneTools/docs/comms_module.html
GramophoneTools/docs/comms_overview.html
GramophoneTools/docs/event.html
GramophoneTools/docs/frame.html
GramophoneTools/docs/genindex.html
GramophoneTools/docs/gramrec.html
GramophoneTools/docs/gramrec_out.html
GramophoneTools/docs/index.html
GramophoneTools/docs/level.html
GramophoneTools/docs/linmaze.html
GramophoneTools/docs/linmaze_main.html
GramophoneTools/docs/linmaze_out.html
GramophoneTools/docs/objects.inv
GramophoneTools/docs/py-modindex.html
GramophoneTools/docs/rule.html
GramophoneTools/docs/search.html
GramophoneTools/docs/searchindex.js
GramophoneTools/docs/user_guide.html
GramophoneTools/docs/zone.html
GramophoneTools/docs/_downloads/a94417d0800bb8600dab2d1445026e29/Gramophone User Guide.pdf
GramophoneTools/docs/_modules/Event.html
GramophoneTools-0.7.1.dist-info/LICENSE
GramophoneTools-0.7.1.dist-info/METADATA
GramophoneTools-0.7.1.dist-info/WHEEL
GramophoneTools-0.7.1.dist-info/entry_points.txt
GramophoneTools-0.7.1.dist-info/top_level.txt
GramophoneTools-0.7.1.dist-info/RECORD
