Metadata-Version: 2.1
Name: GramophoneTools
Version: 0.7.1
Summary: Tools for Gramophone systems by Femtonics Ltd.
Home-page: http://femtonics.eu/
Author: Femtonics Ltd.
Author-email: info@femtonics.eu
License: GNU GPLv3
Project-URL: GitHub, https://github.com/Femtonics/GramophoneTools
Project-URL: Documentation, http://gramophone.femtonics.eu
Project-URL: User Guide, http://gramophone.femtonics.eu/_downloads/Gramophone%20User%20Guide.pdf
Project-URL: Product page, https://femtonics.eu/products/#nav-gramophone-accessories
Keywords: femtonics gramophone
Platform: UNKNOWN
Classifier: Development Status :: 4 - Beta
Classifier: Topic :: Scientific/Engineering
Classifier: Intended Audience :: Science/Research
Classifier: License :: OSI Approved :: GNU General Public License v3 (GPLv3)
Classifier: Operating System :: Microsoft :: Windows :: Windows 10
Classifier: Programming Language :: Python :: 3.6
Requires-Python: >=3
Requires-Dist: h5py
Requires-Dist: PyQt5
Requires-Dist: numpy
Requires-Dist: dill
Requires-Dist: pillow
Requires-Dist: pyglet (==1.3.2)
Requires-Dist: pyqtgraph
Requires-Dist: matplotlib
Requires-Dist: opencv-python
Requires-Dist: pyusb
Requires-Dist: xlsxwriter
Provides-Extra: docs
Requires-Dist: sphinx ; extra == 'docs'
Requires-Dist: sphinx-rtd-theme ; extra == 'docs'
Provides-Extra: tests
Requires-Dist: pytest ; extra == 'tests'
